{
  "user": [
    {
      "name": "mary",
      "email": "mary@gmail.com",
      "password": "a123",
      "id": "1"
    },
    {
      "id": "4e05",
      "name": "regw",
      "email": "832@gmail.com",
      "password": "fwf2"
    },
    {
      "id": "5eb0",
      "name": "272tyr",
      "email": "475@gmail.com",
      "password": "rre45"
    },
    {
      "id": "81e8",
      "name": "eff2fj",
      "email": "wfq@gamil.com",
      "password": "d1d1"
    },
    {
      "id": "318a",
      "name": "e2f2",
      "email": "d1wd@gmail.com",
      "password": "fbejp"
    },
    {
      "id": "2d43",
      "name": "wfew",
      "email": "f2efjo@gmail.com",
      "password": "fbips"
    },
    {
      "id": "f4aa",
      "name": "",
      "email": "",
      "password": ""
    },
    {
      "id": "7d7e",
      "name": "",
      "email": "",
      "password": ""
    },
    {
      "id": "41ea",
      "name": "",
      "email": "",
      "password": ""
    },
    {
      "id": "2b61",
      "name": "",
      "email": "",
      "password": ""
    },
    {
      "id": "6f6f",
      "name": "",
      "email": "",
      "password": ""
    },
    {
      "id": "fe84",
      "name": "廖謙順",
      "email": "ca9n@gmail.com",
      "password": "fwefhio"
    },
    {
      "id": "98a0",
      "name": "廖謙順",
      "email": "ca9n@gmail.com",
      "password": "fwefhio"
    },
    {
      "id": "8161",
      "name": "廖謙順",
      "email": "ca9n@gmail.com",
      "password": "fwefhio"
    },
    {
      "id": "7ddd",
      "name": "fw",
      "email": "fwegf@gail.con",
      "password": "eq"
    },
    {
      "id": "b2a6",
      "username": "timothy83",
      "useremail": "1111@gmail.com",
      "userpassword": "adfwefAA"
    },
    {
      "id": "6974",
      "username": "timothy83",
      "useremail": "1111@gmail.com",
      "userpassword": "adfwefAA"
    },
    {
      "id": "aa42",
      "username": "廖謙順",
      "useremail": "1111@gmail.com",
      "userpassword": "f2jeifo2F"
    },
    {
      "id": "409c",
      "username": "timothy83",
      "useremail": "1111@gmail.com",
      "userpassword": "Dferger"
    },
    {
      "id": "654b",
      "username": "timothy83",
      "useremail": "1111@gmail.com",
      "userpassword": "Das1"
    },
    {
      "id": "23ee",
      "username": "timothy83",
      "useremail": "1111@gmail.com",
      "userpassword": "Das1"
    },
    {
      "id": "9e42",
      "username": "timothy83",
      "useremail": "1111@gmail.com",
      "userpassword": "45654Da"
    },
    {
      "id": "8b65",
      "username": "timothy83",
      "useremail": "1111@gmail.com",
      "userpassword": "45654Da"
    },
    {
      "id": "dacb",
      "username": "timothy83",
      "useremail": "ddd@gmail.com",
      "userpassword": "r2r2ADE2D"
    },
    {
      "id": "8d32",
      "email": "1111@gmail.com",
      "password": "ad2dAED"
    },
    {
      "id": "16a9",
      "email": "1111@gmail.com",
      "password": "ad2dAED"
    },
    {
      "id": "ef1b",
      "email": "1111@gmail.com",
      "password": "13213ssA"
    },
    {
      "username": "timothy83",
      "useremail": "1111@gmail.com",
      "userpassword": "16546Aq",
      "id": "cIk5JoX"
    }
  ]
}